flask_paseto_extended/__init__.py
flask_paseto_extended/config.py
flask_paseto_extended/cookie_session.py
flask_paseto_extended/exceptions.py
flask_paseto_extended/issuer.py
flask_paseto_extended/login_manager.py
flask_paseto_extended/py.typed
flask_paseto_extended/token.py
flask_paseto_extended/utils.py
flask_paseto_extended/verifier.py
flask_paseto_extended-0.6.4.dist-info/licenses/LICENSE
flask_paseto_extended-0.6.4.dist-info/WHEEL
flask_paseto_extended-0.6.4.dist-info/METADATA
flask_paseto_extended-0.6.4.dist-info/RECORD
