Metadata-Version: 2.4
Name: flask-paseto-extended
Version: 0.6.4
Summary: PASETO (Platform-Agnostic Security Tokens) for Flask applications.
Author: Ajitomi Daisuke
Author-email: Ajitomi Daisuke <dajiaji@gmail.com>
License-Expression: MIT
License-File: LICENSE
Classifier: License :: OSI Approved :: MIT License
Classifier: Programming Language :: Python
Classifier: Programming Language :: Python :: 3
Classifier: Programming Language :: Python :: 3 :: Only
Classifier: Programming Language :: Python :: 3.10
Classifier: Programming Language :: Python :: 3.11
Classifier: Programming Language :: Python :: 3.12
Classifier: Programming Language :: Python :: 3.13
Classifier: Programming Language :: Python :: 3.14
Classifier: Framework :: Flask
Classifier: Typing :: Typed
Requires-Dist: werkzeug>=3,<4
Requires-Dist: flask>3,<4
Requires-Dist: flask-login>=0.6.3,<0.7
Requires-Dist: pyseto>=1.7.8,<2
Requires-Python: >=3.10, <4.0
Project-URL: Repository, https://github.com/dajiaji/flask-paseto-extended
